Metadata-Version: 2.4
Name: rgmol
Version: 0.1.4.4
Summary: Visualization and computation of various chemical properties from DFT softwares. Its main purpose is to compute and visualize the condensed and non-condensed linear response function from CDFT.
Author-email: Rémi Grincourt <remi.grincourt@ens-lyon.fr>
License: MIT License
Project-URL: Repository, https://github.com/re-gr/rgmol
Project-URL: Documentation, https://re-gr.github.io/re-gr/rgmol_wiki
Keywords: molecule,representation,dft,cdft,visualization,chemistry
Classifier: Development Status :: 4 - Beta
Classifier: Programming Language :: Python :: 3.12
Requires-Python: >=3.9
Requires-Dist: numpy
Requires-Dist: scipy
Requires-Dist: periodictable
Requires-Dist: pyvista
Requires-Dist: matplotlib
